Workbook
Name Quantidade_de_Anos: Aplicativo!$D$17
Name Rendimento_do_Portfólio: Aplicativo!$D$11
Name Taxa_de_Rendimento_Mensal: Aplicativo!$D$18
Name Taxa_mês: Aplicativo!$D$18
Name tx_mês: Aplicativo!$D$18
Name Valor_Acumulado: Aplicativo!$D$19
Name Valor_Investido: Aplicativo!$D$16

Sheet Aplicativo
B9: Parâmetros
B10: Salário | D10: 5000
B11: Rendimento do Portfólio | D11: 0.006
B12: % do Salário para Investir | D12: 0.2
B13: Saldo Investido | D13: =D10*D12 -> 1000
B15: Investimento Mensal
B16: Valor Investido | D16: 2000
B17: Quantidade de Anos | D17: 10
B18: Taxa de Rendimento Mensal | D18: 0.01079
B19: Valor Acumulado | D19: =FV(Taxa_de_Rendimento_Mensal,Quantidade_de_Anos*12,Valor_Investido*-1) -> 486568.43
B20: Dividendos Mensais | D20: =Valor_Acumulado*Rendimento_do_Portfólio -> 2919.4106
B22: Cenários | C22: Montante | D22: Dividendos
A23: 2 | B23: 2 anos | C23: =FV(Taxa_de_Rendimento_Mensal,A23*12,Valor_Investido*-1) -> 54455.255 | D23: =C23*Rendimento_do_Portfólio -> 326.73153
A24: 5 | B24: 5 anos | C24: =FV(Taxa_de_Rendimento_Mensal,A24*12,Valor_Investido*-1) -> 167553.83 | D24: =C24*Rendimento_do_Portfólio -> 1005.323
A25: 10 | B25: 10 anos | C25: =FV(Taxa_de_Rendimento_Mensal,A25*12,Valor_Investido*-1) -> 486568.43 | D25: =C25*Rendimento_do_Portfólio -> 2919.4106
A26: 15 | B26: 15 anos | C26: =FV(Taxa_de_Rendimento_Mensal,A26*12,Valor_Investido*-1) -> 1093957.2 | D26: =C26*Rendimento_do_Portfólio -> 6563.7432
A27: 20 | B27: 20 anos | C27: =FV(Taxa_de_Rendimento_Mensal,A27*12,Valor_Investido*-1) -> 2250396.8 | D27: =C27*Rendimento_do_Portfólio -> 13502.381
A28: 25 | B28: 25 anos | C28: =FV(Taxa_de_Rendimento_Mensal,A28*12,Valor_Investido*-1) -> 4452203.3 | D28: =C28*Rendimento_do_Portfólio -> 26713.22
A29: 30 | B29: 30 anos | C29: =FV(Taxa_de_Rendimento_Mensal,A29*12,Valor_Investido*-1) -> 8644339.3 | D29: =C29*Rendimento_do_Portfólio -> 51866.036
B32: Simulação Por Perfil
B33: Perfil | D33: Conservador
B34: Valor Investido | D34: =Valor_Investido -> 2000
B36: Tipos de FIIs | C36: % Sugerido | D36: Valores
B37: Tijolo | C37: =VLOOKUP($D$33&"-"&B37,Apoio!$I$3:$L$20,4,0) -> 0.5 | D37: =C37*$D$34 -> 1000
B38: Papel | C38: =VLOOKUP($D$33&"-"&B38,Apoio!$I$3:$L$20,4,0) -> 0.3 | D38: =C38*$D$34 -> 600
B39: Fundos de Fundos (FoF) | C39: =VLOOKUP($D$33&"-"&B39,Apoio!$I$3:$L$20,4,0) -> 0 | D39: =C39*$D$34 -> 0
B40: Híbridos | C40: =VLOOKUP($D$33&"-"&B40,Apoio!$I$3:$L$20,4,0) -> 0.1 | D40: =C40*$D$34 -> 200
B41: Fiagros | C41: =VLOOKUP($D$33&"-"&B41,Apoio!$I$3:$L$20,4,0) -> 0.05 | D41: =C41*$D$34 -> 100
B42: Desenvolvimento | C42: =VLOOKUP($D$33&"-"&B42,Apoio!$I$3:$L$20,4,0) -> 0.05 | D42: =C42*$D$34 -> 100

Sheet Apoio
B2: Percentuais de Alocação Salário | D2: Tipos de FIIs | F2: Perfis | G2: Check dos % | I2: Chave (ID) | J2: Perfil | K2: Tipo de FII | L2: %
B3: 0.1 | D3: Tijolo | F3: Conservador | G3: =SUMIF($J$3:$L$20,$F$3,$L$3:$L$20) -> 1 | I3: =$F$3&"-"&$D3 -> Conservador-Tijolo | J3: Conservador | K3: Tijolo | L3: 0.5
B4: 0.2 | D4: Papel | F4: Moderado | G4: =SUMIF($J$3:$L$20,$F$3,$L$3:$L$20) -> 1 | I4: =$F$3&"-"&$D4 -> Conservador-Papel | J4: Conservador | K4: Papel | L4: 0.3
B5: 0.3 | D5: Fundos de Fundos (FoF) | F5: Agressivo | G5: =SUMIF($J$3:$L$20,$F$3,$L$3:$L$20) -> 1 | I5: =$F$3&"-"&$D5 -> Conservador-Fundos de Fundos (FoF) | J5: Conservador | K5: Fundos de Fundos (FoF) | L5: 0
B6: 0.4 | D6: Híbridos | I6: =$F$3&"-"&$D6 -> Conservador-Híbridos | J6: Conservador | K6: Híbridos | L6: 0.1
B7: 0.5 | D7: Fiagros | I7: =$F$3&"-"&$D7 -> Conservador-Fiagros | J7: Conservador | K7: Fiagros | L7: 0.05
B8: 0.6 | D8: Desenvolvimento | I8: =$F$3&"-"&$D8 -> Conservador-Desenvolvimento | J8: Conservador | K8: Desenvolvimento | L8: 0.05
B9: 0.7 | I9: =$F$4&"-"&$D3 -> Moderado-Tijolo | J9: Moderado | K9: Tijolo | L9: 0.3
B10: 0.8 | I10: =$F$4&"-"&$D4 -> Moderado-Papel | J10: Moderado | K10: Papel | L10: 0.3
B11: 0.9 | I11: =$F$4&"-"&$D5 -> Moderado-Fundos de Fundos (FoF) | J11: Moderado | K11: Fundos de Fundos (FoF) | L11: 0.2
B12: 1 | I12: =$F$4&"-"&$D6 -> Moderado-Híbridos | J12: Moderado | K12: Híbridos | L12: 0.1
I13: =$F$4&"-"&$D7 -> Moderado-Fiagros | J13: Moderado | K13: Fiagros | L13: 0.05
I14: =$F$4&"-"&$D8 -> Moderado-Desenvolvimento | J14: Moderado | K14: Desenvolvimento | L14: 0.05
I15: =$F$5&"-"&$D3 -> Agressivo-Tijolo | J15: Agressivo | K15: Tijolo | L15: 0.15
I16: =$F$5&"-"&$D4 -> Agressivo-Papel | J16: Agressivo | K16: Papel | L16: 0.45
I17: =$F$5&"-"&$D5 -> Agressivo-Fundos de Fundos (FoF) | J17: Agressivo | K17: Fundos de Fundos (FoF) | L17: 0.15
I18: =$F$5&"-"&$D6 -> Agressivo-Híbridos | J18: Agressivo | K18: Híbridos | L18: 0.1
I19: =$F$5&"-"&$D7 -> Agressivo-Fiagros | J19: Agressivo | K19: Fiagros | L19: 0.05
I20: =$F$5&"-"&$D8 -> Agressivo-Desenvolvimento | J20: Agressivo | K20: Desenvolvimento | L20: 0.1
